newscenter/__init__.py
newscenter/admin.py
newscenter/feeds.py
newscenter/forms.py
newscenter/managers.py
newscenter/migrations/0001_initial.py
newscenter/migrations/0002_auto_20170124_1042.py
newscenter/migrations/0003_newsroom_website.py
newscenter/migrations/0004_auto_20180104_1119.py
newscenter/migrations/__init__.py
newscenter/models.py
newscenter/sitemaps.py
newscenter/static/newscenter/css/newscenter.css
newscenter/static/newscenter/img/feed-icon-14x14.png
newscenter/static/newscenter/img/feed-icon-28x28.png
newscenter/static/newscenter/js/bxslider/images/bx_loader.gif
newscenter/static/newscenter/js/bxslider/images/controls.png
newscenter/static/newscenter/js/bxslider/jquery.bxslider.css
newscenter/static/newscenter/js/bxslider/jquery.bxslider.min.js
newscenter/static/newscenter/js/bxslider/plugins/jquery.easing.1.3.js
newscenter/static/newscenter/js/bxslider/plugins/jquery.fitvids.js
newscenter/static/newscenter/js/jquery.min.js
newscenter/static/newscenter/js/popeye/img/bg1.png
newscenter/static/newscenter/js/popeye/img/compact1.png
newscenter/static/newscenter/js/popeye/img/compact2.png
newscenter/static/newscenter/js/popeye/img/compact3.png
newscenter/static/newscenter/js/popeye/img/compact4.png
newscenter/static/newscenter/js/popeye/img/enlarge1.png
newscenter/static/newscenter/js/popeye/img/enlarge2.png
newscenter/static/newscenter/js/popeye/img/enlarge3.png
newscenter/static/newscenter/js/popeye/img/enlarge4.png
newscenter/static/newscenter/js/popeye/img/loading1.gif
newscenter/static/newscenter/js/popeye/img/loading2.gif
newscenter/static/newscenter/js/popeye/img/loading3.gif
newscenter/static/newscenter/js/popeye/img/next1.png
newscenter/static/newscenter/js/popeye/img/next3.png
newscenter/static/newscenter/js/popeye/img/prev1.png
newscenter/static/newscenter/js/popeye/img/prev3.png
newscenter/static/newscenter/js/popeye/jquery.popeye-2.0.4.min.js
newscenter/static/newscenter/js/popeye/jquery.popeye.css
newscenter-4.0.2.dist-info/WHEEL
newscenter-4.0.2.dist-info/METADATA
newscenter-4.0.2.dist-info/RECORD
