Metadata-Version: 2.1
Name: newscenter
Version: 4.0.2
Summary: A News Release Application for Django
Home-page: https://github.com/ImaginaryLandscape/django-newscenter
License: MIT
Author: Imaginary Landscape
Author-email: info@imagescape.com
Requires-Python: >=3.7,<4.0
Classifier: License :: OSI Approved :: MIT License
Classifier: Programming Language :: Python :: 3
Classifier: Programming Language :: Python :: 3.7
Classifier: Programming Language :: Python :: 3.8
Classifier: Programming Language :: Python :: 3.9
Requires-Dist: Pillow (>=9.0.0,<10.0.0)
Requires-Dist: django-el-pagination (>=3.0.0,<4.0.0)
Requires-Dist: easy-thumbnails (>=2.8.0,<3.0.0)
Requires-Dist: feedparser (>=6.0.0,<7.0.0)
Requires-Dist: site-config (>=2.0.0,<3.0.0)
